tests
labjack
