Metadata-Version: 1.0
Name: labjacku12
Version: 0.4
Summary: LabJack U12 driver
Home-page: http://www.phys.ethz.ch/~robertjo/labjacku12
Author: Robert Jordens
Author-email: jordens@phys.ethz.ch
License: BSD
Platform: UNKNOWN
